LICENSE
MANIFEST.in
README.md
setup.cfg
setup.py
pydot/__init__.py
pydot/dot_parser.py
pydot/pydot.py
pydot3.egg-info/PKG-INFO
pydot3.egg-info/SOURCES.txt
pydot3.egg-info/dependency_links.txt
pydot3.egg-info/requires.txt
pydot3.egg-info/top_level.txt